{
  "mini-css-extract-plugin node_modules/css-loader/index.js??ref--5-1!assets/styles/main.css": [
    {
      "modules": {
        "byIdentifier": {
          "node_modules/css-loader/index.js??ref--5-1!assets/styles/main.css": 0,
          "node_modules/css-loader/lib/css-base.js": 1
        },
        "usedIds": {
          "0": 0,
          "1": 1
        }
      },
      "chunks": {
        "byName": {
          "mini-css-extract-plugin": 0
        },
        "bySource": {},
        "usedIds": [
          0
        ]
      }
    }
  ],
  "mini-css-extract-plugin node_modules/css-loader/index.js??ref--5-1!assets/styles/addCompany.css": [
    {
      "modules": {
        "byIdentifier": {
          "node_modules/css-loader/index.js??ref--5-1!assets/styles/addCompany.css": 0,
          "node_modules/css-loader/lib/css-base.js": 1
        },
        "usedIds": {
          "0": 0,
          "1": 1
        }
      },
      "chunks": {
        "byName": {
          "mini-css-extract-plugin": 0
        },
        "bySource": {},
        "usedIds": [
          0
        ]
      }
    }
  ],
  "mini-css-extract-plugin node_modules/css-loader/index.js??ref--5-1!assets/styles/companyContact.css": [
    {
      "modules": {
        "byIdentifier": {
          "node_modules/css-loader/index.js??ref--5-1!assets/styles/companyContact.css": 0,
          "node_modules/css-loader/lib/css-base.js": 1
        },
        "usedIds": {
          "0": 0,
          "1": 1
        }
      },
      "chunks": {
        "byName": {
          "mini-css-extract-plugin": 0
        },
        "bySource": {},
        "usedIds": [
          0
        ]
      }
    }
  ],
  "mini-css-extract-plugin node_modules/css-loader/index.js??ref--5-1!assets/styles/categoryManagement.css": [
    {
      "modules": {
        "byIdentifier": {
          "node_modules/css-loader/index.js??ref--5-1!assets/styles/categoryManagement.css": 0,
          "node_modules/css-loader/lib/css-base.js": 1
        },
        "usedIds": {
          "0": 0,
          "1": 1
        }
      },
      "chunks": {
        "byName": {
          "mini-css-extract-plugin": 0
        },
        "bySource": {},
        "usedIds": [
          0
        ]
      }
    }
  ],
  "mini-css-extract-plugin node_modules/css-loader/index.js??ref--5-1!node_modules/react-table/react-table.css": [
    {
      "modules": {
        "byIdentifier": {
          "node_modules/css-loader/index.js??ref--5-1!node_modules/react-table/react-table.css": 0,
          "node_modules/css-loader/lib/css-base.js": 1
        },
        "usedIds": {
          "0": 0,
          "1": 1
        }
      },
      "chunks": {
        "byName": {
          "mini-css-extract-plugin": 0
        },
        "bySource": {},
        "usedIds": [
          0
        ]
      }
    }
  ],
  "mini-css-extract-plugin node_modules/css-loader/index.js??ref--5-1!assets/styles/companyContactSidebar.css": [
    {
      "modules": {
        "byIdentifier": {
          "node_modules/css-loader/index.js??ref--5-1!assets/styles/companyContactSidebar.css": 0,
          "node_modules/css-loader/lib/css-base.js": 1
        },
        "usedIds": {
          "0": 0,
          "1": 1
        }
      },
      "chunks": {
        "byName": {
          "mini-css-extract-plugin": 0
        },
        "bySource": {},
        "usedIds": [
          0
        ]
      }
    }
  ],
  "modules": {
    "byIdentifier": {
      "node_modules/react/index.js": 0,
      "node_modules/semantic-ui-react/node_modules/@babel/runtime/helpers/assertThisInitialized.js": 1,
      "node_modules/semantic-ui-react/node_modules/@babel/runtime/helpers/defineProperty.js": 2,
      "node_modules/prop-types/index.js": 3,
      "node_modules/semantic-ui-react/node_modules/@babel/runtime/helpers/extends.js": 4,
      "node_modules/classnames/index.js": 5,
      "node_modules/semantic-ui-react/dist/es/lib/index.js ac4be3fec1b5eca72cc706ec2de5d7fc": 6,
      "node_modules/lodash/invoke.js": 7,
      "node_modules/semantic-ui-react/node_modules/@babel/runtime/helpers/getPrototypeOf.js": 8,
      "node_modules/semantic-ui-react/node_modules/@babel/runtime/helpers/classCallCheck.js": 9,
      "node_modules/semantic-ui-react/node_modules/@babel/runtime/helpers/createClass.js": 10,
      "node_modules/semantic-ui-react/node_modules/@babel/runtime/helpers/possibleConstructorReturn.js": 11,
      "node_modules/semantic-ui-react/node_modules/@babel/runtime/helpers/inherits.js": 12,
      "node_modules/lodash/isNil.js": 13,
      "node_modules/semantic-ui-react/node_modules/@babel/runtime/helpers/objectSpread.js": 14,
      "node_modules/keyboard-key/src/keyboardKey.js": 15,
      "node_modules/lodash/get.js": 16,
      "node_modules/lodash/map.js": 17,
      "node_modules/lodash/isArray.js": 18,
      "node_modules/lodash/includes.js": 19,
      "node_modules/lodash/without.js": 20,
      "node_modules/semantic-ui-react/node_modules/@babel/runtime/helpers/slicedToArray.js": 21,
      "node_modules/core-js/library/modules/_core.js": 22,
      "node_modules/lodash/isObjectLike.js": 23,
      "node_modules/lodash/some.js": 24,
      "node_modules/lodash/isEmpty.js": 25,
      "node_modules/lodash/_root.js": 26,
      "node_modules/lodash/fp/placeholder.js": 27,
      "node_modules/core-js/library/modules/_export.js": 28,
      "node_modules/lodash/isArrayLike.js": 29,
      "node_modules/lodash/fp/convert.js": 30,
      "node_modules/semantic-ui-react/dist/es/elements/Icon/index.js": 31,
      "node_modules/core-js/library/modules/_global.js": 32,
      "node_modules/@babel/runtime-corejs2/helpers/interopRequireDefault.js": 33,
      "node_modules/lodash/isObject.js": 34,
      "node_modules/lodash/toString.js": 35,
      "node_modules/superagent/lib/client.js": 36,
      "node_modules/core-js/library/modules/_wks.js": 37,
      "node_modules/lodash/_getTag.js": 38,
      "node_modules/semantic-ui-react/node_modules/@babel/runtime/helpers/typeof.js": 39,
      "node_modules/lodash/isUndefined.js": 40,
      "node_modules/next/link.js": 41,
      "node_modules/core-js/library/modules/_is-object.js": 42,
      "node_modules/@babel/runtime-corejs2/helpers/classCallCheck.js": 43,
      "node_modules/@babel/runtime-corejs2/helpers/createClass.js": 44,
      "node_modules/lodash/_baseIteratee.js": 45,
      "node_modules/lodash/_baseGetTag.js": 46,
      "node_modules/lodash/isFunction.js": 47,
      "node_modules/react-dom/index.js": 48,
      "node_modules/lodash/forEach.js": 49,
      "node_modules/lodash/keys.js": 50,
      "node_modules/lodash/toInteger.js": 51,
      "node_modules/lodash/reduce.js": 52,
      "node_modules/lodash/pick.js": 53,
      "node_modules/lodash/filter.js": 54,
      "node_modules/lodash/deburr.js": 55,
      "node_modules/@babel/runtime/regenerator/index.js": 56,
      "node_modules/core-js/library/modules/_object-dp.js": 57,
      "node_modules/core-js/library/modules/_an-object.js": 58,
      "node_modules/lodash/identity.js": 59,
      "node_modules/lodash/_hasUnicode.js": 60,
      "node_modules/lodash/_copyArray.js": 61,
      "node_modules/lodash/inRange.js": 62,
      "node_modules/lodash/size.js": 63,
      "node_modules/lodash/union.js": 64,
      "node_modules/core-js/library/modules/_descriptors.js": 65,
      "node_modules/lodash/_arrayMap.js": 66,
      "node_modules/lodash/_toKey.js": 67,
      "node_modules/lodash/_baseEach.js": 68,
      "node_modules/lodash/isString.js": 69,
      "node_modules/next/dist/build/webpack/loaders/next-babel-loader.js??ref--4!assets/common-components/componentHead.js": 70,
      "node_modules/core-js/library/modules/_ctx.js": 71,
      "node_modules/@babel/runtime-corejs2/helpers/defineProperty.js": 72,
      "node_modules/lodash/_Symbol.js": 73,
      "node_modules/lodash/_baseUnary.js": 74,
      "node_modules/lodash/_castPath.js": 75,
      "node_modules/lodash/_baseFlatten.js": 76,
      "node_modules/lodash/_assignValue.js": 77,
      "node_modules/lodash/_flatRest.js": 78,
      "node_modules/lodash/_stringToArray.js": 79,
      "node_modules/lodash/_createCtor.js": 80,
      "node_modules/lodash/_baseCreate.js": 81,
      "node_modules/lodash/_copyObject.js": 82,
      "node_modules/semantic-ui-react/dist/es/elements/Label/index.js": 83,
      "node_modules/semantic-ui-react/dist/es/modules/Checkbox/index.js": 84,
      "node_modules/semantic-ui-react/dist/es/modules/Dropdown/index.js": 85,
      "node_modules/core-js/library/modules/_fails.js": 86,
      "node_modules/core-js/library/modules/_hide.js": 87,
      "node_modules/@babel/runtime-corejs2/helpers/possibleConstructorReturn.js": 88,
      "node_modules/@babel/runtime-corejs2/helpers/getPrototypeOf.js": 89,
      "node_modules/@babel/runtime-corejs2/helpers/inherits.js": 90,
      "node_modules/semantic-ui-react/dist/es/lib/classNameBuilders.js": 91,
      "node_modules/lodash/_isIndex.js": 92,
      "node_modules/semantic-ui-react/node_modules/@babel/runtime/helpers/toConsumableArray.js": 93,
      "node_modules/semantic-ui-react/dist/es/elements/Label/Label.js fba20fdf0829176690a643448f6058b1": 94,
      "node_modules/semantic-ui-react/dist/es/lib/htmlPropsUtils.js": 95,
      "node_modules/semantic-ui-react/dist/es/elements/Icon/Icon.js 53235bae95b9d3cd050c787d49b94f8d": 96,
      "node_modules/lodash/first.js": 97,
      "node_modules/@semantic-ui-react/event-stack/lib/index.js": 98,
      "node_modules/semantic-ui-react/node_modules/@babel/runtime/helpers/get.js": 99,
      "node_modules/lodash/compact.js": 100,
      "node_modules/lodash/every.js": 101,
      "node_modules/lodash/escapeRegExp.js": 102,
      "node_modules/lodash/dropRight.js": 103,
      "node_modules/lodash/isEqual.js": 104,
      "node_modules/shallowequal/index.js": 105,
      "node_modules/lodash/sum.js": 106,
      "node_modules/lodash/startCase.js": 107,
      "node_modules/next/dist/build/webpack/loaders/next-babel-loader.js??ref--4!assets/common-components/CompanyContactSidebar.js 61b5b7df9fdb49a3cfa9093565e8d1cf": 108,
      "node_modules/lodash/find.js": 109,
      "node_modules/next/dist/build/webpack/loaders/next-babel-loader.js??ref--4!assets/common-components/TopMenuBar.js": 110,
      "node_modules/react-table/es/index.js f1c7d2211a0646a681e47d29e4ff7f56": 111,
      "node_modules/semantic-ui-react/dist/es/addons/Ref/index.js": 112,
      "node_modules/semantic-ui-react/dist/es/elements/Button/index.js": 113,
      "node_modules/semantic-ui-react/dist/es/index.js": 114,
      "node_modules/@babel/runtime-corejs2/helpers/interopRequireWildcard.js": 115,
      "node_modules/core-js/library/modules/_to-iobject.js": 116,
      "node_modules/core-js/library/modules/_has.js": 117,
      "node_modules/core-js/library/modules/_a-function.js": 118,
      "node_modules/core-js/library/modules/es6.string.iterator.js": 119,
      "node_modules/next/dist/lib/utils.js": 120,
      "node_modules/lodash/_getNative.js": 121,
      "node_modules/lodash/_nodeUtil.js": 122,
      "node_modules/lodash/_baseKeys.js": 123,
      "node_modules/lodash/values.js": 124,
      "node_modules/lodash/_arrayEach.js": 125,
      "node_modules/lodash/_baseSlice.js": 126,
      "node_modules/lodash/_baseRest.js": 127,
      "node_modules/lodash/_baseAssignValue.js": 128,
      "node_modules/lodash/_castSlice.js": 129,
      "node_modules/lodash/_createWrap.js": 130,
      "node_modules/lodash/_LazyWrapper.js": 131,
      "node_modules/lodash/_baseLodash.js": 132,
      "node_modules/lodash/_getData.js": 133,
      "node_modules/lodash/_LodashWrapper.js": 134,
      "node_modules/lodash/_replaceHolders.js": 135,
      "node_modules/lodash/_cloneArrayBuffer.js": 136,
      "node_modules/lodash/fp/_falseOptions.js": 137,
      "node_modules/lodash/findIndex.js": 138,
      "node_modules/lodash/difference.js": 139,
      "node_modules/core-js/library/modules/_to-object.js": 140,
      "node_modules/@babel/runtime-corejs2/core-js/promise.js": 141,
      "node_modules/core-js/library/modules/_iterators.js": 142,
      "node_modules/core-js/library/modules/web.dom.iterable.js": 143,
      "node_modules/webpack/buildin/module.js": 144,
      "node_modules/lodash/eq.js": 145,
      "node_modules/lodash/_isPrototype.js": 146,
      "node_modules/lodash/_baseGet.js": 147,
      "node_modules/lodash/isSymbol.js": 148,
      "node_modules/lodash/_isIterateeCall.js": 149,
      "node_modules/lodash/_apply.js": 150,
      "node_modules/lodash/_setToString.js": 151,
      "node_modules/lodash/isArrayLikeObject.js": 152,
      "node_modules/lodash/_arrayReduce.js": 153,
      "node_modules/semantic-ui-react/dist/es/lib/numberToWord.js": 154,
      "node_modules/semantic-ui-react/dist/es/addons/Radio/index.js": 155,
      "node_modules/semantic-ui-react/dist/es/elements/Image/index.js": 156,
      "node_modules/core-js/library/modules/_cof.js": 157,
      "node_modules/core-js/library/modules/_property-desc.js": 158,
      "node_modules/core-js/library/modules/_library.js": 159,
      "node_modules/core-js/library/modules/_set-to-string-tag.js": 160,
      "node_modules/core-js/library/modules/_object-keys.js": 161,
      "node_modules/core-js/library/modules/_object-create.js": 162,
      "node_modules/core-js/library/modules/_for-of.js": 163,
      "node_modules/next/dist/lib/router/index.js": 164,
      "node_modules/lodash/_baseIsEqual.js": 165,
      "node_modules/lodash/_setToArray.js": 166,
      "node_modules/lodash/_getSymbols.js": 167,
      "node_modules/lodash/isBuffer.js": 168,
      "node_modules/semantic-ui-react/node_modules/@babel/runtime/helpers/arrayWithHoles.js": 169,
      "node_modules/semantic-ui-react/node_modules/@babel/runtime/helpers/iterableToArrayLimit.js": 170,
      "node_modules/semantic-ui-react/node_modules/@babel/runtime/helpers/nonIterableRest.js": 171,
      "node_modules/lodash/_baseValues.js": 172,
      "node_modules/lodash/_baseInRange.js": 173,
      "node_modules/lodash/head.js": 174,
      "node_modules/@semantic-ui-react/event-stack/lib/cjs/event-stack.production.js": 175,
      "node_modules/exenv/index.js": 176,
      "node_modules/lodash/_arrayIncludes.js": 177,
      "node_modules/lodash/_getPrototype.js": 178,
      "node_modules/semantic-ui-react/node_modules/@babel/runtime/helpers/arrayWithoutHoles.js": 179,
      "node_modules/semantic-ui-react/node_modules/@babel/runtime/helpers/iterableToArray.js": 180,
      "node_modules/semantic-ui-react/node_modules/@babel/runtime/helpers/nonIterableSpread.js": 181,
      "node_modules/semantic-ui-react/node_modules/@babel/runtime/helpers/superPropBase.js": 182,
      "node_modules/lodash/_arrayEvery.js": 183,
      "node_modules/lodash/_baseEvery.js": 184,
      "node_modules/lodash/_baseReduce.js": 185,
      "node_modules/lodash/_basePick.js": 186,
      "node_modules/lodash/_basePickBy.js": 187,
      "node_modules/lodash/_baseSet.js": 188,
      "node_modules/lodash/flatten.js": 189,
      "node_modules/lodash/_stringSize.js": 190,
      "node_modules/lodash/_asciiSize.js": 191,
      "node_modules/lodash/_unicodeSize.js": 192,
      "node_modules/lodash/_baseSum.js": 193,
      "node_modules/lodash/_createCompounder.js": 194,
      "node_modules/lodash/words.js": 195,
      "node_modules/lodash/_asciiWords.js": 196,
      "node_modules/lodash/_hasUnicodeWord.js": 197,
      "node_modules/lodash/_unicodeWords.js": 198,
      "node_modules/lodash/upperFirst.js": 199,
      "node_modules/lodash/_createCaseFirst.js": 200,
      "node_modules/lodash/_asciiToArray.js": 201,
      "node_modules/lodash/_unicodeToArray.js": 202,
      "node_modules/lodash/_baseSetData.js": 203,
      "node_modules/lodash/_metaMap.js": 204,
      "node_modules/lodash/_createHybrid.js": 205,
      "node_modules/lodash/_composeArgs.js": 206,
      "node_modules/lodash/_composeArgsRight.js": 207,
      "node_modules/lodash/_createRecurry.js": 208,
      "node_modules/lodash/_isLaziable.js": 209,
      "node_modules/lodash/_getFuncName.js": 210,
      "node_modules/lodash/_setData.js": 211,
      "node_modules/lodash/_setWrapToString.js": 212,
      "node_modules/lodash/_getHolder.js": 213,
      "node_modules/lodash/_baseAssign.js": 214,
      "node_modules/lodash/_baseClone.js": 215,
      "node_modules/lodash/keysIn.js": 216,
      "node_modules/lodash/_getSymbolsIn.js": 217,
      "node_modules/semantic-ui-react/dist/es/elements/Image/Image.js f812f3d19f305348745e0cab8315fc7a": 218,
      "node_modules/lodash/fp/uniq.js": 219,
      "node_modules/lodash/fp/identity.js": 220,
      "node_modules/lodash/fp/filter.js": 221,
      "node_modules/lodash/fp/split.js": 222,
      "node_modules/lodash/fp/flatMap.js": 223,
      "node_modules/lodash/fp/map.js": 224,
      "node_modules/lodash/fp/toArray.js": 225,
      "node_modules/lodash/fp/flow.js": 226,
      "node_modules/semantic-ui-react/dist/es/addons/Portal/index.js": 227,
      "node_modules/core-js/library/modules/_object-pie.js": 228,
      "node_modules/@babel/runtime-corejs2/core-js/object/define-property.js": 229,
      "node_modules/@babel/runtime-corejs2/helpers/objectSpread.js": 230,
      "node_modules/core-js/library/modules/_uid.js": 231,
      "node_modules/core-js/library/modules/_to-length.js": 232,
      "node_modules/@babel/runtime-corejs2/regenerator/index.js": 233,
      "node_modules/@babel/runtime-corejs2/helpers/asyncToGenerator.js": 234,
      "node_modules/core-js/library/modules/es6.object.to-string.js": 235,
      "node_modules/core-js/library/modules/_classof.js": 236,
      "node_modules/@babel/runtime-corejs2/helpers/typeof.js": 237,
      "node_modules/@babel/runtime-corejs2/core-js/set.js": 238,
      "node_modules/@babel/runtime-corejs2/helpers/assertThisInitialized.js": 239,
      "node_modules/lodash/_Stack.js": 240,
      "node_modules/lodash/_ListCache.js": 241,
      "node_modules/lodash/_assocIndexOf.js": 242,
      "node_modules/lodash/_nativeCreate.js": 243,
      "node_modules/lodash/_getMapData.js": 244,
      "node_modules/lodash/_SetCache.js": 245,
      "node_modules/lodash/_cacheHas.js": 246,
      "node_modules/lodash/_arrayPush.js": 247,
      "node_modules/lodash/isArguments.js": 248,
      "node_modules/lodash/_baseToString.js": 249,
      "node_modules/lodash/hasIn.js": 250,
      "node_modules/lodash/_baseProperty.js": 251,
      "node_modules/lodash/toFinite.js": 252,
      "node_modules/lodash/toNumber.js": 253,
      "node_modules/lodash/_baseIndexOf.js": 254,
      "node_modules/semantic-ui-react/dist/es/lib/isBrowser.js": 255,
      "node_modules/lodash/_overRest.js": 256,
      "node_modules/lodash/_defineProperty.js": 257,
      "node_modules/semantic-ui-react/dist/es/lib/doesNodeContainClick.js": 258,
      "node_modules/semantic-ui-react/dist/es/lib/eventStack/index.js": 259,
      "node_modules/lodash/has.js": 260,
      "node_modules/lodash/_baseUniq.js": 261,
      "node_modules/semantic-ui-react/dist/es/lib/shallowEqual.js": 262,
      "node_modules/lodash/uniq.js": 263,
      "node_modules/lodash/isPlainObject.js": 264,
      "node_modules/core-js/library/modules/_iobject.js": 265,
      "node_modules/core-js/library/modules/_defined.js": 266,
      "node_modules/core-js/library/modules/_object-gopd.js": 267,
      "node_modules/core-js/library/modules/_to-primitive.js": 268,
      "node_modules/core-js/library/modules/_dom-create.js": 269,
      "node_modules/core-js/library/modules/_object-sap.js": 270,
      "node_modules/core-js/library/modules/_meta.js": 271,
      "node_modules/core-js/library/modules/_shared.js": 272,
      "node_modules/core-js/library/modules/_wks-ext.js": 273,
      "node_modules/core-js/library/modules/_wks-define.js": 274,
      "node_modules/core-js/library/modules/_to-integer.js": 275,
      "node_modules/core-js/library/modules/_shared-key.js": 276,
      "node_modules/core-js/library/modules/_enum-bug-keys.js": 277,
      "node_modules/core-js/library/modules/_object-gops.js": 278,
      "node_modules/core-js/library/modules/_is-array.js": 279,
      "node_modules/core-js/library/modules/_iter-define.js": 280,
      "node_modules/core-js/library/modules/_an-instance.js": 281,
      "node_modules/core-js/library/modules/core.get-iterator-method.js": 282,
      "node_modules/core-js/library/modules/_new-promise-capability.js": 283,
      "node_modules/core-js/library/modules/_redefine-all.js": 284,
      "node_modules/@babel/runtime-corejs2/helpers/slicedToArray.js": 285,
      "node_modules/@babel/runtime-corejs2/core-js/array/is-array.js": 286,
      "node_modules/core-js/library/modules/_validate-collection.js": 287,
      "node_modules/next/dist/lib/EventEmitter.js": 288,
      "node_modules/@babel/runtime-corejs2/core-js/object/assign.js": 289,
      "node_modules/lodash/_Map.js": 290,
      "node_modules/lodash/_MapCache.js": 291,
      "node_modules/lodash/_Uint8Array.js": 292,
      "node_modules/lodash/_mapToArray.js": 293,
      "node_modules/lodash/_getAllKeys.js": 294,
      "node_modules/lodash/_baseGetAllKeys.js": 295,
      "node_modules/lodash/stubArray.js": 296,
      "node_modules/lodash/_arrayLikeKeys.js": 297,
      "node_modules/lodash/isTypedArray.js": 298,
      "node_modules/lodash/isLength.js": 299,
      "node_modules/lodash/_WeakMap.js": 300,
      "node_modules/lodash/_isKey.js": 301,
      "node_modules/lodash/_stringToPath.js": 302,
      "node_modules/lodash/_shortOut.js": 303,
      "node_modules/lodash/_arrayIncludesWith.js": 304,
      "node_modules/lodash/noop.js": 305,
      "node_modules/mini-css-extract-plugin/dist/loader.js!node_modules/css-loader/index.js??ref--5-1!assets/styles/companyContactSidebar.css": 306,
      "node_modules/mini-css-extract-plugin/dist/loader.js!node_modules/css-loader/index.js??ref--5-1!node_modules/react-table/react-table.css": 307,
      "node_modules/lodash/fp/_baseConvert.js": 308,
      "node_modules/lodash/fp/_mapping.js": 309,
      "node_modules/lodash/fp/_util.js": 310,
      "node_modules/lodash/ary.js": 311,
      "node_modules/lodash/_createBind.js": 312,
      "node_modules/lodash/_createCurry.js": 313,
      "node_modules/lodash/_countHolders.js": 314,
      "node_modules/lodash/_realNames.js": 315,
      "node_modules/lodash/wrapperLodash.js": 316,
      "node_modules/lodash/_wrapperClone.js": 317,
      "node_modules/lodash/_getWrapDetails.js": 318,
      "node_modules/lodash/_insertWrapDetails.js": 319,
      "node_modules/lodash/_updateWrapDetails.js": 320,
      "node_modules/lodash/_reorder.js": 321,
      "node_modules/lodash/_createPartial.js": 322,
      "node_modules/lodash/_mergeData.js": 323,
      "node_modules/lodash/clone.js": 324,
      "node_modules/lodash/_baseAssignIn.js": 325,
      "node_modules/lodash/_baseKeysIn.js": 326,
      "node_modules/lodash/_nativeKeysIn.js": 327,
      "node_modules/lodash/_cloneBuffer.js": 328,
      "node_modules/lodash/_copySymbols.js": 329,
      "node_modules/lodash/_copySymbolsIn.js": 330,
      "node_modules/lodash/_getAllKeysIn.js": 331,
      "node_modules/lodash/_initCloneArray.js": 332,
      "node_modules/lodash/_initCloneByTag.js": 333,
      "node_modules/lodash/_cloneDataView.js": 334,
      "node_modules/lodash/_cloneRegExp.js": 335,
      "node_modules/lodash/_cloneSymbol.js": 336,
      "node_modules/lodash/_cloneTypedArray.js": 337,
      "node_modules/lodash/_initCloneObject.js": 338,
      "node_modules/lodash/isMap.js": 339,
      "node_modules/lodash/_baseIsMap.js": 340,
      "node_modules/lodash/isSet.js": 341,
      "node_modules/lodash/_baseIsSet.js": 342,
      "node_modules/lodash/curry.js": 343,
      "node_modules/lodash/isError.js": 344,
      "node_modules/lodash/isWeakMap.js": 345,
      "node_modules/lodash/iteratee.js": 346,
      "node_modules/lodash/rearg.js": 347,
      "node_modules/lodash/toPath.js": 348,
      "node_modules/lodash/split.js": 349,
      "node_modules/lodash/isRegExp.js": 350,
      "node_modules/lodash/_baseIsRegExp.js": 351,
      "node_modules/lodash/flatMap.js": 352,
      "node_modules/lodash/toArray.js": 353,
      "node_modules/lodash/_iteratorToArray.js": 354,
      "node_modules/lodash/flow.js": 355,
      "node_modules/lodash/_createFlow.js": 356,
      "node_modules/next/app.js": 357,
      "node_modules/semantic-ui-react/dist/es/addons/Select/index.js": 358,
      "node_modules/semantic-ui-react/dist/es/addons/TextArea/index.js": 359,
      "node_modules/semantic-ui-react/dist/es/elements/Flag/index.js": 360,
      "node_modules/semantic-ui-react/dist/es/elements/Input/index.js": 361,
      "node_modules/semantic-ui-react/dist/es/lib/childMapping.js": 362,
      "node_modules/semantic-ui-react/dist/es/lib/debug.js": 363,
      "node_modules/semantic-ui-react/dist/es/modules/Dimmer/index.js": 364,
      "node_modules/@babel/runtime-corejs2/core-js/object/get-own-property-descriptor.js": 365,
      "node_modules/core-js/library/modules/_ie8-dom-define.js": 366,
      "node_modules/core-js/library/modules/es6.symbol.js": 367,
      "node_modules/core-js/library/modules/_redefine.js": 368,
      "node_modules/core-js/library/modules/_object-keys-internal.js": 369,
      "node_modules/core-js/library/modules/_html.js": 370,
      "node_modules/core-js/library/modules/_object-gopn.js": 371,
      "node_modules/@babel/runtime-corejs2/core-js/object/keys.js": 372,
      "node_modules/regenerator-runtime/runtime-module.js": 373,
      "node_modules/core-js/library/modules/_object-gpo.js": 374,
      "node_modules/core-js/library/modules/_iter-step.js": 375,
      "node_modules/core-js/library/modules/_iter-call.js": 376,
      "node_modules/core-js/library/modules/_is-array-iter.js": 377,
      "node_modules/core-js/library/modules/_species-constructor.js": 378,
      "node_modules/core-js/library/modules/_task.js": 379,
      "node_modules/core-js/library/modules/_invoke.js": 380,
      "node_modules/core-js/library/modules/_perform.js": 381,
      "node_modules/core-js/library/modules/_promise-resolve.js": 382,
      "node_modules/core-js/library/modules/_set-species.js": 383,
      "node_modules/core-js/library/modules/_iter-detect.js": 384,
      "node_modules/@babel/runtime-corejs2/core-js/get-iterator.js": 385,
      "node_modules/object-assign/index.js": 386,
      "node_modules/@babel/runtime-corejs2/helpers/setPrototypeOf.js": 387,
      "node_modules/@babel/runtime-corejs2/core-js/object/set-prototype-of.js": 388,
      "node_modules/core-js/library/modules/_collection-strong.js": 389,
      "node_modules/core-js/library/modules/_collection.js": 390,
      "node_modules/core-js/library/modules/_collection-to-json.js": 391,
      "node_modules/core-js/library/modules/_set-collection-of.js": 392,
      "node_modules/core-js/library/modules/_set-collection-from.js": 393,
      "node_modules/url/url.js": 394,
      "node_modules/webpack/buildin/global.js": 395,
      "node_modules/mini-css-extract-plugin/dist/loader.js!node_modules/css-loader/index.js??ref--5-1!assets/styles/main.css": 396,
      "node_modules/superagent/lib/is-object.js": 397,
      "node_modules/next/dist/lib/head.js": 398,
      "node_modules/mini-css-extract-plugin/dist/loader.js!node_modules/css-loader/index.js??ref--5-1!assets/styles/addCompany.css": 399,
      "node_modules/semantic-ui-react/dist/es/lib/getUnhandledProps.js": 400,
      "node_modules/semantic-ui-react/dist/es/lib/getElementType.js": 401,
      "node_modules/lodash/_freeGlobal.js": 402,
      "node_modules/lodash/_toSource.js": 403,
      "node_modules/lodash/_equalArrays.js": 404,
      "node_modules/lodash/_arraySome.js": 405,
      "node_modules/lodash/_arrayFilter.js": 406,
      "node_modules/lodash/_overArg.js": 407,
      "node_modules/lodash/_Set.js": 408,
      "node_modules/lodash/_isStrictComparable.js": 409,
      "node_modules/lodash/_matchesStrictComparable.js": 410,
      "node_modules/lodash/_hasPath.js": 411,
      "node_modules/lodash/_baseFindIndex.js": 412,
      "node_modules/semantic-ui-react/dist/es/addons/Ref/Ref.js": 413,
      "node_modules/semantic-ui-react/dist/es/lib/AutoControlledComponent.js": 414,
      "node_modules/lodash/_baseDifference.js": 415,
      "node_modules/semantic-ui-react/dist/es/lib/factories.js": 416,
      "node_modules/semantic-ui-react/dist/es/collections/Form/Form.js f9585dd1ae37969fcddb341fc2308708": 417,
      "node_modules/semantic-ui-react/dist/es/modules/Dropdown/Dropdown.js 37586adf18439cf222e6b393b2f7b943": 418,
      "node_modules/semantic-ui-react/dist/es/views/Card/Card.js b3ee73b0a4fa305893be08979657cd0c": 419,
      "node_modules/semantic-ui-react/dist/es/elements/Button/Button.js 0b48d0912eab2fd5c33829951a8357d0": 420,
      "node_modules/semantic-ui-react/dist/es/addons/Portal/Portal.js a74547377d9a28f6560f87ff6d8e26ab": 421,
      "node_modules/styled-jsx/style.js": 422,
      "node_modules/next/head.js": 423,
      "node_modules/lodash/isNumber.js": 424,
      "node_modules/lodash/isBoolean.js": 425,
      "node_modules/next/router.js": 426,
      "node_modules/semantic-ui-react/dist/es/addons/MountNode/index.js": 427,
      "node_modules/semantic-ui-react/dist/es/lib/SUI.js": 428,
      "node_modules/semantic-ui-react/dist/es/lib/createPaginationItems/index.js": 429,
      "node_modules/semantic-ui-react/dist/es/lib/customPropTypes.js": 430,
      "node_modules/semantic-ui-react/dist/es/lib/leven.js": 431,
      "node_modules/semantic-ui-react/dist/es/lib/normalizeOffset.js": 432,
      "node_modules/semantic-ui-react/dist/es/lib/normalizeTransitionDuration.js": 433,
      "node_modules/semantic-ui-react/dist/es/lib/objectDiff.js": 434,
      "multi node_modules/next/dist/client/next": 435,
      "node_modules/next/dist/client/next.js": 436,
      "node_modules/core-js/library/fn/object/get-own-property-descriptor.js": 437,
      "node_modules/core-js/library/modules/es6.object.get-own-property-descriptor.js": 438,
      "node_modules/core-js/library/fn/object/define-property.js": 439,
      "node_modules/core-js/library/modules/es6.object.define-property.js": 440,
      "node_modules/next/dist/client/index.js": 441,
      "node_modules/@babel/runtime-corejs2/core-js/object/get-own-property-symbols.js": 442,
      "node_modules/core-js/library/fn/object/get-own-property-symbols.js": 443,
      "node_modules/core-js/library/modules/_enum-keys.js": 444,
      "node_modules/core-js/library/modules/_array-includes.js": 445,
      "node_modules/core-js/library/modules/_to-absolute-index.js": 446,
      "node_modules/core-js/library/modules/_object-dps.js": 447,
      "node_modules/core-js/library/modules/_object-gopn-ext.js": 448,
      "node_modules/core-js/library/fn/object/keys.js": 449,
      "node_modules/core-js/library/modules/es6.object.keys.js": 450,
      "node_modules/regenerator-runtime/runtime.js": 451,
      "node_modules/core-js/library/fn/promise.js": 452,
      "node_modules/core-js/library/modules/_string-at.js": 453,
      "node_modules/core-js/library/modules/_iter-create.js": 454,
      "node_modules/core-js/library/modules/es6.array.iterator.js": 455,
      "node_modules/core-js/library/modules/_add-to-unscopables.js": 456,
      "node_modules/core-js/library/modules/es6.promise.js": 457,
      "node_modules/core-js/library/modules/_microtask.js": 458,
      "node_modules/core-js/library/modules/_user-agent.js": 459,
      "node_modules/core-js/library/modules/es7.promise.finally.js": 460,
      "node_modules/core-js/library/modules/es7.promise.try.js": 461,
      "node_modules/@babel/runtime-corejs2/helpers/arrayWithHoles.js": 462,
      "node_modules/core-js/library/fn/array/is-array.js": 463,
      "node_modules/core-js/library/modules/es6.array.is-array.js": 464,
      "node_modules/@babel/runtime-corejs2/helpers/iterableToArrayLimit.js": 465,
      "node_modules/core-js/library/fn/get-iterator.js": 466,
      "node_modules/core-js/library/modules/core.get-iterator.js": 467,
      "node_modules/@babel/runtime-corejs2/helpers/nonIterableRest.js": 468,
      "node_modules/react/cjs/react.production.min.js": 469,
      "node_modules/react-dom/cjs/react-dom.production.min.js": 470,
      "node_modules/scheduler/index.js": 471,
      "node_modules/scheduler/cjs/scheduler.production.min.js": 472,
      "node_modules/next/dist/client/head-manager.js": 473,
      "node_modules/@babel/runtime-corejs2/core-js/symbol/iterator.js": 474,
      "node_modules/core-js/library/fn/symbol/iterator.js": 475,
      "node_modules/@babel/runtime-corejs2/core-js/symbol.js": 476,
      "node_modules/core-js/library/fn/symbol/index.js": 477,
      "node_modules/core-js/library/modules/es7.symbol.async-iterator.js": 478,
      "node_modules/core-js/library/modules/es7.symbol.observable.js": 479,
      "node_modules/@babel/runtime-corejs2/helpers/construct.js": 480,
      "node_modules/@babel/runtime-corejs2/core-js/reflect/construct.js": 481,
      "node_modules/core-js/library/fn/reflect/construct.js": 482,
      "node_modules/core-js/library/modules/es6.reflect.construct.js": 483,
      "node_modules/core-js/library/modules/_bind.js": 484,
      "node_modules/core-js/library/fn/object/set-prototype-of.js": 485,
      "node_modules/core-js/library/modules/es6.object.set-prototype-of.js": 486,
      "node_modules/core-js/library/modules/_set-proto.js": 487,
      "node_modules/next/dist/lib/router/router.js": 488,
      "node_modules/core-js/library/fn/set.js": 489,
      "node_modules/core-js/library/modules/es6.set.js": 490,
      "node_modules/core-js/library/modules/_array-methods.js": 491,
      "node_modules/core-js/library/modules/_array-species-create.js": 492,
      "node_modules/core-js/library/modules/_array-species-constructor.js": 493,
      "node_modules/core-js/library/modules/es7.set.to-json.js": 494,
      "node_modules/core-js/library/modules/_array-from-iterable.js": 495,
      "node_modules/core-js/library/modules/es7.set.of.js": 496,
      "node_modules/core-js/library/modules/es7.set.from.js": 497,
      "node_modules/node-libs-browser/node_modules/punycode/punycode.js": 498,
      "node_modules/url/util.js": 499,
      "node_modules/querystring-es3/index.js": 500,
      "node_modules/querystring-es3/decode.js": 501,
      "node_modules/querystring-es3/encode.js": 502,
      "node_modules/next/dist/lib/shallow-equals.js": 503,
      "node_modules/next/dist/lib/p-queue.js": 504,
      "node_modules/core-js/library/fn/object/assign.js": 505,
      "node_modules/core-js/library/modules/es6.object.assign.js": 506,
      "node_modules/core-js/library/modules/_object-assign.js": 507,
      "node_modules/next/dist/lib/router/with-router.js": 508,
      "node_modules/@babel/runtime-corejs2/core-js/object/get-prototype-of.js": 509,
      "node_modules/core-js/library/fn/object/get-prototype-of.js": 510,
      "node_modules/core-js/library/modules/es6.object.get-prototype-of.js": 511,
      "node_modules/@babel/runtime-corejs2/core-js/object/create.js": 512,
      "node_modules/core-js/library/fn/object/create.js": 513,
      "node_modules/core-js/library/modules/es6.object.create.js": 514,
      "node_modules/prop-types/factoryWithThrowingShims.js": 515,
      "node_modules/prop-types/lib/ReactPropTypesSecret.js": 516,
      "node_modules/hoist-non-react-statics/dist/hoist-non-react-statics.cjs.js": 517,
      "node_modules/next/dist/lib/page-loader.js": 518,
      "node_modules/next/dist/lib/asset.js": 519,
      "node_modules/next/dist/lib/runtime-config.js": 520,
      "node_modules/next/dist/client/error-boundary.js": 521,
      "node_modules/next/dist/lib/loadable.js": 522,
      "node_modules/@babel/runtime-corejs2/core-js/map.js": 523,
      "node_modules/core-js/library/fn/map.js": 524,
      "node_modules/core-js/library/modules/es6.map.js": 525,
      "node_modules/core-js/library/modules/es7.map.to-json.js": 526,
      "node_modules/core-js/library/modules/es7.map.of.js": 527,
      "node_modules/core-js/library/modules/es7.map.from.js": 528,
      "multi ./pages/_app.js": 529,
      "node_modules/next/dist/build/webpack/loaders/next-babel-loader.js??ref--4!pages/_app.js": 530,
      "node_modules/next/dist/lib/app.js": 531,
      "node_modules/@babel/runtime-corejs2/helpers/extends.js": 532,
      "css node_modules/css-loader/index.js??ref--5-1!assets/styles/main.css 0": 533,
      "multi ./pages/_index.js": 534,
      "node_modules/next/dist/build/webpack/loaders/next-babel-loader.js??ref--4!pages/_index.js": 535,
      "node_modules/styled-jsx/dist/style.js": 536,
      "node_modules/styled-jsx/dist/stylesheet-registry.js": 537,
      "node_modules/string-hash/index.js": 538,
      "node_modules/styled-jsx/dist/lib/stylesheet.js": 539,
      "node_modules/process/browser.js": 540,
      "node_modules/component-emitter/index.js": 541,
      "node_modules/superagent/lib/request-base.js": 542,
      "node_modules/superagent/lib/response-base.js": 543,
      "node_modules/superagent/lib/utils.js": 544,
      "node_modules/superagent/lib/agent-base.js": 545,
      "multi ./pages/add-company.js": 546,
      "node_modules/next/dist/build/webpack/loaders/next-babel-loader.js??ref--4!pages/add-company.js": 547,
      "node_modules/next/dist/lib/side-effect.js": 548,
      "node_modules/@babel/runtime-corejs2/helpers/toConsumableArray.js": 549,
      "node_modules/@babel/runtime-corejs2/helpers/arrayWithoutHoles.js": 550,
      "node_modules/@babel/runtime-corejs2/helpers/iterableToArray.js": 551,
      "node_modules/@babel/runtime-corejs2/core-js/array/from.js": 552,
      "node_modules/core-js/library/fn/array/from.js": 553,
      "node_modules/core-js/library/modules/es6.array.from.js": 554,
      "node_modules/core-js/library/modules/_create-property.js": 555,
      "node_modules/@babel/runtime-corejs2/core-js/is-iterable.js": 556,
      "node_modules/core-js/library/fn/is-iterable.js": 557,
      "node_modules/core-js/library/modules/core.is-iterable.js": 558,
      "node_modules/@babel/runtime-corejs2/helpers/nonIterableSpread.js": 559,
      "css node_modules/css-loader/index.js??ref--5-1!assets/styles/addCompany.css 0": 560,
      "node_modules/semantic-ui-react/node_modules/@babel/runtime/helpers/setPrototypeOf.js": 561,
      "node_modules/lodash/_createFind.js": 562,
      "node_modules/lodash/_baseMatches.js": 563,
      "node_modules/lodash/_baseIsMatch.js": 564,
      "node_modules/lodash/_listCacheClear.js": 565,
      "node_modules/lodash/_listCacheDelete.js": 566,
      "node_modules/lodash/_listCacheGet.js": 567,
      "node_modules/lodash/_listCacheHas.js": 568,
      "node_modules/lodash/_listCacheSet.js": 569,
      "node_modules/lodash/_stackClear.js": 570,
      "node_modules/lodash/_stackDelete.js": 571,
      "node_modules/lodash/_stackGet.js": 572,
      "node_modules/lodash/_stackHas.js": 573,
      "node_modules/lodash/_stackSet.js": 574,
      "node_modules/lodash/_baseIsNative.js": 575,
      "node_modules/lodash/_getRawTag.js": 576,
      "node_modules/lodash/_objectToString.js": 577,
      "node_modules/lodash/_isMasked.js": 578,
      "node_modules/lodash/_coreJsData.js": 579,
      "node_modules/lodash/_getValue.js": 580,
      "node_modules/lodash/_mapCacheClear.js": 581,
      "node_modules/lodash/_Hash.js": 582,
      "node_modules/lodash/_hashClear.js": 583,
      "node_modules/lodash/_hashDelete.js": 584,
      "node_modules/lodash/_hashGet.js": 585,
      "node_modules/lodash/_hashHas.js": 586,
      "node_modules/lodash/_hashSet.js": 587,
      "node_modules/lodash/_mapCacheDelete.js": 588,
      "node_modules/lodash/_isKeyable.js": 589,
      "node_modules/lodash/_mapCacheGet.js": 590,
      "node_modules/lodash/_mapCacheHas.js": 591,
      "node_modules/lodash/_mapCacheSet.js": 592,
      "node_modules/lodash/_baseIsEqualDeep.js": 593,
      "node_modules/lodash/_setCacheAdd.js": 594,
      "node_modules/lodash/_setCacheHas.js": 595,
      "node_modules/lodash/_equalByTag.js": 596,
      "node_modules/lodash/_equalObjects.js": 597,
      "node_modules/lodash/_baseTimes.js": 598,
      "node_modules/lodash/_baseIsArguments.js": 599,
      "node_modules/lodash/stubFalse.js": 600,
      "node_modules/lodash/_baseIsTypedArray.js": 601,
      "node_modules/lodash/_nativeKeys.js": 602,
      "node_modules/lodash/_DataView.js": 603,
      "node_modules/lodash/_Promise.js": 604,
      "node_modules/lodash/_getMatchData.js": 605,
      "node_modules/lodash/_baseMatchesProperty.js": 606,
      "node_modules/lodash/_memoizeCapped.js": 607,
      "node_modules/lodash/memoize.js": 608,
      "node_modules/lodash/_baseHasIn.js": 609,
      "node_modules/lodash/property.js": 610,
      "node_modules/lodash/_basePropertyDeep.js": 611,
      "node_modules/lodash/_baseSome.js": 612,
      "node_modules/lodash/_baseForOwn.js": 613,
      "node_modules/lodash/_baseFor.js": 614,
      "node_modules/lodash/_createBaseFor.js": 615,
      "node_modules/lodash/_createBaseEach.js": 616,
      "node_modules/lodash/_baseIsNaN.js": 617,
      "node_modules/lodash/_strictIndexOf.js": 618,
      "node_modules/lodash/_castFunction.js": 619,
      "node_modules/lodash/_baseInvoke.js": 620,
      "node_modules/lodash/last.js": 621,
      "node_modules/lodash/_parent.js": 622,
      "node_modules/lodash/_baseSetToString.js": 623,
      "node_modules/lodash/constant.js": 624,
      "node_modules/lodash/_isFlattenable.js": 625,
      "node_modules/lodash/startsWith.js": 626,
      "node_modules/lodash/_baseClamp.js": 627,
      "node_modules/lodash/_baseFilter.js": 628,
      "node_modules/lodash/intersection.js": 629,
      "node_modules/lodash/_baseIntersection.js": 630,
      "node_modules/lodash/_castArrayLikeObject.js": 631,
      "node_modules/lodash/_baseHas.js": 632,
      "node_modules/lodash/each.js": 633,
      "node_modules/lodash/_createSet.js": 634,
      "node_modules/lodash/_baseMap.js": 635,
      "node_modules/lodash/_deburrLetter.js": 636,
      "node_modules/lodash/_basePropertyOf.js": 637,
      "multi ./pages/company-contact/category.js": 638,
      "node_modules/next/dist/lib/link.js": 639,
      "node_modules/@babel/runtime-corejs2/core-js/json/stringify.js": 640,
      "node_modules/core-js/library/fn/json/stringify.js": 641,
      "css node_modules/css-loader/index.js??ref--5-1!assets/styles/companyContactSidebar.css 0": 642,
      "node_modules/mini-css-extract-plugin/dist/loader.js!node_modules/css-loader/index.js??ref--5-1!assets/styles/categoryManagement.css": 643,
      "css node_modules/css-loader/index.js??ref--5-1!assets/styles/categoryManagement.css 0": 644,
      "css node_modules/css-loader/index.js??ref--5-1!node_modules/react-table/react-table.css 0": 645,
      "multi ./pages/company-contact/company.js": 646,
      "multi ./pages/company-contact/index.js": 647,
      "node_modules/next/dist/build/webpack/loaders/next-babel-loader.js??ref--4!pages/company-contact/index.js": 648,
      "node_modules/mini-css-extract-plugin/dist/loader.js!node_modules/css-loader/index.js??ref--5-1!assets/styles/companyContact.css": 649,
      "css node_modules/css-loader/index.js??ref--5-1!assets/styles/companyContact.css 0": 650,
      "multi ./pages/index.js": 651,
      "node_modules/next/dist/build/webpack/loaders/next-babel-loader.js??ref--4!pages/index.js": 652,
      "multi node_modules/next/dist/pages/_error.js": 653,
      "node_modules/next/dist/pages/_error.js": 654,
      "node_modules/next/error.js": 655,
      "node_modules/next/dist/lib/error.js": 656,
      "node_modules/http-status/lib/index.js": 657,
      "node_modules/semantic-ui-react/dist/es/modules/Modal/Modal.js 41f88eb0c2fc54b23a82648fe385dd5d": 658,
      "node_modules/next/dist/build/webpack/loaders/next-babel-loader.js??ref--4!pages/company-contact/category.js 704ecee7c9141c857f1bff783f18aa9c": 659,
      "node_modules/next/dist/build/webpack/loaders/next-babel-loader.js??ref--4!pages/company-contact/company.js 2d8bd22da8f006e997ad8f735d781eae": 660,
      "node_modules/lodash/_arrayAggregator.js": 661,
      "node_modules/lodash/_baseAggregator.js": 662,
      "node_modules/lodash/_baseExtremum.js": 663,
      "node_modules/lodash/_baseLt.js": 664,
      "node_modules/lodash/_baseOrderBy.js": 665,
      "node_modules/lodash/_baseRange.js": 666,
      "node_modules/lodash/_baseSortBy.js": 667,
      "node_modules/lodash/_charsEndIndex.js": 668,
      "node_modules/lodash/_charsStartIndex.js": 669,
      "node_modules/lodash/_compareAscending.js": 670,
      "node_modules/lodash/_compareMultiple.js": 671,
      "node_modules/lodash/_createAggregator.js": 672,
      "node_modules/lodash/_createAssigner.js": 673,
      "node_modules/lodash/_createRange.js": 674,
      "node_modules/lodash/_createRound.js": 675,
      "node_modules/lodash/assign.js": 676,
      "node_modules/lodash/clamp.js": 677,
      "node_modules/lodash/fp/compact.js": 678,
      "node_modules/lodash/fp/difference.js": 679,
      "node_modules/lodash/fp/isFunction.js": 680,
      "node_modules/lodash/fp/isNil.js": 681,
      "node_modules/lodash/fp/isObject.js": 682,
      "node_modules/lodash/fp/isPlainObject.js": 683,
      "node_modules/lodash/fp/keys.js": 684,
      "node_modules/lodash/fp/memoize.js": 685,
      "node_modules/lodash/fp/min.js": 686,
      "node_modules/lodash/fp/pick.js": 687,
      "node_modules/lodash/fp/sortBy.js": 688,
      "node_modules/lodash/fp/sum.js": 689,
      "node_modules/lodash/fp/take.js": 690,
      "node_modules/lodash/fp/trim.js": 691,
      "node_modules/lodash/keyBy.js": 692,
      "node_modules/lodash/mapValues.js": 693,
      "node_modules/lodash/min.js": 694,
      "node_modules/lodash/partialRight.js": 695,
      "node_modules/lodash/pickBy.js": 696,
      "node_modules/lodash/range.js": 697,
      "node_modules/lodash/round.js": 698,
      "node_modules/lodash/sortBy.js": 699,
      "node_modules/lodash/take.js": 700,
      "node_modules/lodash/times.js": 701,
      "node_modules/lodash/transform.js": 702,
      "node_modules/lodash/trim.js": 703,
      "node_modules/semantic-ui-react/dist/es/addons/Confirm/Confirm.js": 704,
      "node_modules/semantic-ui-react/dist/es/addons/Confirm/index.js": 705,
      "node_modules/semantic-ui-react/dist/es/addons/Pagination/Pagination.js": 706,
      "node_modules/semantic-ui-react/dist/es/addons/Pagination/PaginationItem.js": 707,
      "node_modules/semantic-ui-react/dist/es/addons/Pagination/index.js": 708,
      "node_modules/semantic-ui-react/dist/es/addons/Responsive/Responsive.js": 709,
      "node_modules/semantic-ui-react/dist/es/addons/Responsive/index.js": 710,
      "node_modules/semantic-ui-react/dist/es/addons/TransitionablePortal/TransitionablePortal.js": 711,
      "node_modules/semantic-ui-react/dist/es/addons/TransitionablePortal/index.js": 712,
      "node_modules/semantic-ui-react/dist/es/behaviors/Visibility/Visibility.js": 713,
      "node_modules/semantic-ui-react/dist/es/behaviors/Visibility/index.js": 714,
      "node_modules/semantic-ui-react/dist/es/collections/Breadcrumb/Breadcrumb.js": 715,
      "node_modules/semantic-ui-react/dist/es/collections/Breadcrumb/BreadcrumbDivider.js": 716,
      "node_modules/semantic-ui-react/dist/es/collections/Breadcrumb/BreadcrumbSection.js": 717,
      "node_modules/semantic-ui-react/dist/es/collections/Breadcrumb/index.js": 718,
      "node_modules/semantic-ui-react/dist/es/collections/Form/index.js": 719,
      "node_modules/semantic-ui-react/dist/es/collections/Grid/Grid.js": 720,
      "node_modules/semantic-ui-react/dist/es/collections/Grid/GridColumn.js": 721,
      "node_modules/semantic-ui-react/dist/es/collections/Grid/GridRow.js": 722,
      "node_modules/semantic-ui-react/dist/es/collections/Grid/index.js": 723,
      "node_modules/semantic-ui-react/dist/es/collections/Menu/index.js": 724,
      "node_modules/semantic-ui-react/dist/es/collections/Message/Message.js": 725,
      "node_modules/semantic-ui-react/dist/es/collections/Message/MessageContent.js": 726,
      "node_modules/semantic-ui-react/dist/es/collections/Message/MessageHeader.js": 727,
      "node_modules/semantic-ui-react/dist/es/collections/Message/MessageItem.js": 728,
      "node_modules/semantic-ui-react/dist/es/collections/Message/MessageList.js": 729,
      "node_modules/semantic-ui-react/dist/es/collections/Message/index.js": 730,
      "node_modules/semantic-ui-react/dist/es/collections/Table/Table.js": 731,
      "node_modules/semantic-ui-react/dist/es/collections/Table/TableBody.js": 732,
      "node_modules/semantic-ui-react/dist/es/collections/Table/TableCell.js": 733,
      "node_modules/semantic-ui-react/dist/es/collections/Table/TableFooter.js": 734,
      "node_modules/semantic-ui-react/dist/es/collections/Table/TableHeader.js": 735,
      "node_modules/semantic-ui-react/dist/es/collections/Table/TableHeaderCell.js": 736,
      "node_modules/semantic-ui-react/dist/es/collections/Table/TableRow.js": 737,
      "node_modules/semantic-ui-react/dist/es/collections/Table/index.js": 738,
      "node_modules/semantic-ui-react/dist/es/elements/Container/Container.js": 739,
      "node_modules/semantic-ui-react/dist/es/elements/Container/index.js": 740,
      "node_modules/semantic-ui-react/dist/es/elements/Divider/Divider.js": 741,
      "node_modules/semantic-ui-react/dist/es/elements/Divider/index.js": 742,
      "node_modules/semantic-ui-react/dist/es/elements/Header/Header.js": 743,
      "node_modules/semantic-ui-react/dist/es/elements/Header/HeaderContent.js": 744,
      "node_modules/semantic-ui-react/dist/es/elements/Header/HeaderSubheader.js": 745,
      "node_modules/semantic-ui-react/dist/es/elements/Header/index.js": 746,
      "node_modules/semantic-ui-react/dist/es/elements/List/List.js": 747,
      "node_modules/semantic-ui-react/dist/es/elements/List/ListContent.js": 748,
      "node_modules/semantic-ui-react/dist/es/elements/List/ListDescription.js": 749,
      "node_modules/semantic-ui-react/dist/es/elements/List/ListHeader.js": 750,
      "node_modules/semantic-ui-react/dist/es/elements/List/ListIcon.js": 751,
      "node_modules/semantic-ui-react/dist/es/elements/List/ListItem.js": 752,
      "node_modules/semantic-ui-react/dist/es/elements/List/ListList.js": 753,
      "node_modules/semantic-ui-react/dist/es/elements/List/index.js": 754,
      "node_modules/semantic-ui-react/dist/es/elements/Loader/Loader.js": 755,
      "node_modules/semantic-ui-react/dist/es/elements/Loader/index.js": 756,
      "node_modules/semantic-ui-react/dist/es/elements/Placeholder/Placeholder.js": 757,
      "node_modules/semantic-ui-react/dist/es/elements/Placeholder/PlaceholderHeader.js": 758,
      "node_modules/semantic-ui-react/dist/es/elements/Placeholder/PlaceholderImage.js": 759,
      "node_modules/semantic-ui-react/dist/es/elements/Placeholder/PlaceholderLine.js": 760,
      "node_modules/semantic-ui-react/dist/es/elements/Placeholder/PlaceholderParagraph.js": 761,
      "node_modules/semantic-ui-react/dist/es/elements/Placeholder/index.js": 762,
      "node_modules/semantic-ui-react/dist/es/elements/Rail/Rail.js": 763,
      "node_modules/semantic-ui-react/dist/es/elements/Rail/index.js": 764,
      "node_modules/semantic-ui-react/dist/es/elements/Reveal/Reveal.js": 765,
      "node_modules/semantic-ui-react/dist/es/elements/Reveal/RevealContent.js": 766,
      "node_modules/semantic-ui-react/dist/es/elements/Reveal/index.js": 767,
      "node_modules/semantic-ui-react/dist/es/elements/Segment/Segment.js": 768,
      "node_modules/semantic-ui-react/dist/es/elements/Segment/SegmentGroup.js": 769,
      "node_modules/semantic-ui-react/dist/es/elements/Segment/SegmentInline.js": 770,
      "node_modules/semantic-ui-react/dist/es/elements/Segment/index.js": 771,
      "node_modules/semantic-ui-react/dist/es/elements/Step/Step.js": 772,
      "node_modules/semantic-ui-react/dist/es/elements/Step/StepContent.js": 773,
      "node_modules/semantic-ui-react/dist/es/elements/Step/StepDescription.js": 774,
      "node_modules/semantic-ui-react/dist/es/elements/Step/StepGroup.js": 775,
      "node_modules/semantic-ui-react/dist/es/elements/Step/StepTitle.js": 776,
      "node_modules/semantic-ui-react/dist/es/elements/Step/index.js": 777,
      "node_modules/semantic-ui-react/dist/es/lib/createPaginationItems/createPaginationItems.js": 778,
      "node_modules/semantic-ui-react/dist/es/lib/createPaginationItems/itemFactories.js": 779,
      "node_modules/semantic-ui-react/dist/es/lib/createPaginationItems/paginationUtils.js": 780,
      "node_modules/semantic-ui-react/dist/es/lib/createPaginationItems/rangeFactories.js": 781,
      "node_modules/semantic-ui-react/dist/es/lib/createPaginationItems/suffixFactories.js": 782,
      "node_modules/semantic-ui-react/dist/es/modules/Accordion/Accordion.js": 783,
      "node_modules/semantic-ui-react/dist/es/modules/Accordion/AccordionAccordion.js": 784,
      "node_modules/semantic-ui-react/dist/es/modules/Accordion/AccordionContent.js": 785,
      "node_modules/semantic-ui-react/dist/es/modules/Accordion/AccordionPanel.js": 786,
      "node_modules/semantic-ui-react/dist/es/modules/Accordion/AccordionTitle.js": 787,
      "node_modules/semantic-ui-react/dist/es/modules/Embed/Embed.js": 788,
      "node_modules/semantic-ui-react/dist/es/modules/Embed/index.js": 789,
      "node_modules/semantic-ui-react/dist/es/modules/Modal/index.js": 790,
      "node_modules/semantic-ui-react/dist/es/modules/Popup/Popup.js": 791,
      "node_modules/semantic-ui-react/dist/es/modules/Popup/PopupContent.js": 792,
      "node_modules/semantic-ui-react/dist/es/modules/Popup/PopupHeader.js": 793,
      "node_modules/semantic-ui-react/dist/es/modules/Popup/index.js": 794,
      "node_modules/semantic-ui-react/dist/es/modules/Progress/Progress.js": 795,
      "node_modules/semantic-ui-react/dist/es/modules/Progress/index.js": 796,
      "node_modules/semantic-ui-react/dist/es/modules/Rating/Rating.js": 797,
      "node_modules/semantic-ui-react/dist/es/modules/Rating/RatingIcon.js": 798,
      "node_modules/semantic-ui-react/dist/es/modules/Rating/index.js": 799,
      "node_modules/semantic-ui-react/dist/es/modules/Search/Search.js": 800,
      "node_modules/semantic-ui-react/dist/es/modules/Search/SearchCategory.js": 801,
      "node_modules/semantic-ui-react/dist/es/modules/Search/SearchResult.js": 802,
      "node_modules/semantic-ui-react/dist/es/modules/Search/SearchResults.js": 803,
      "node_modules/semantic-ui-react/dist/es/modules/Search/index.js": 804,
      "node_modules/semantic-ui-react/dist/es/modules/Sidebar/Sidebar.js": 805,
      "node_modules/semantic-ui-react/dist/es/modules/Sidebar/SidebarPushable.js": 806,
      "node_modules/semantic-ui-react/dist/es/modules/Sidebar/SidebarPusher.js": 807,
      "node_modules/semantic-ui-react/dist/es/modules/Sidebar/index.js": 808,
      "node_modules/semantic-ui-react/dist/es/modules/Sticky/Sticky.js": 809,
      "node_modules/semantic-ui-react/dist/es/modules/Sticky/index.js": 810,
      "node_modules/semantic-ui-react/dist/es/modules/Tab/Tab.js": 811,
      "node_modules/semantic-ui-react/dist/es/modules/Tab/TabPane.js": 812,
      "node_modules/semantic-ui-react/dist/es/modules/Tab/index.js": 813,
      "node_modules/semantic-ui-react/dist/es/modules/Transition/Transition.js": 814,
      "node_modules/semantic-ui-react/dist/es/modules/Transition/TransitionGroup.js": 815,
      "node_modules/semantic-ui-react/dist/es/modules/Transition/index.js": 816,
      "node_modules/semantic-ui-react/dist/es/views/Advertisement/Advertisement.js": 817,
      "node_modules/semantic-ui-react/dist/es/views/Advertisement/index.js": 818,
      "node_modules/semantic-ui-react/dist/es/views/Comment/Comment.js": 819,
      "node_modules/semantic-ui-react/dist/es/views/Comment/CommentAction.js": 820,
      "node_modules/semantic-ui-react/dist/es/views/Comment/CommentActions.js": 821,
      "node_modules/semantic-ui-react/dist/es/views/Comment/CommentAuthor.js": 822,
      "node_modules/semantic-ui-react/dist/es/views/Comment/CommentAvatar.js": 823,
      "node_modules/semantic-ui-react/dist/es/views/Comment/CommentContent.js": 824,
      "node_modules/semantic-ui-react/dist/es/views/Comment/CommentGroup.js": 825,
      "node_modules/semantic-ui-react/dist/es/views/Comment/CommentMetadata.js": 826,
      "node_modules/semantic-ui-react/dist/es/views/Comment/CommentText.js": 827,
      "node_modules/semantic-ui-react/dist/es/views/Comment/index.js": 828,
      "node_modules/semantic-ui-react/dist/es/views/Feed/Feed.js": 829,
      "node_modules/semantic-ui-react/dist/es/views/Feed/FeedContent.js": 830,
      "node_modules/semantic-ui-react/dist/es/views/Feed/FeedDate.js": 831,
      "node_modules/semantic-ui-react/dist/es/views/Feed/FeedEvent.js": 832,
      "node_modules/semantic-ui-react/dist/es/views/Feed/FeedExtra.js": 833,
      "node_modules/semantic-ui-react/dist/es/views/Feed/FeedLabel.js": 834,
      "node_modules/semantic-ui-react/dist/es/views/Feed/FeedLike.js": 835,
      "node_modules/semantic-ui-react/dist/es/views/Feed/FeedMeta.js": 836,
      "node_modules/semantic-ui-react/dist/es/views/Feed/FeedSummary.js": 837,
      "node_modules/semantic-ui-react/dist/es/views/Feed/FeedUser.js": 838,
      "node_modules/semantic-ui-react/dist/es/views/Feed/index.js": 839,
      "node_modules/semantic-ui-react/dist/es/views/Item/Item.js": 840,
      "node_modules/semantic-ui-react/dist/es/views/Item/ItemContent.js": 841,
      "node_modules/semantic-ui-react/dist/es/views/Item/ItemDescription.js": 842,
      "node_modules/semantic-ui-react/dist/es/views/Item/ItemExtra.js": 843,
      "node_modules/semantic-ui-react/dist/es/views/Item/ItemGroup.js": 844,
      "node_modules/semantic-ui-react/dist/es/views/Item/ItemHeader.js": 845,
      "node_modules/semantic-ui-react/dist/es/views/Item/ItemImage.js": 846,
      "node_modules/semantic-ui-react/dist/es/views/Item/ItemMeta.js": 847,
      "node_modules/semantic-ui-react/dist/es/views/Item/index.js": 848,
      "node_modules/semantic-ui-react/dist/es/views/Statistic/Statistic.js": 849,
      "node_modules/semantic-ui-react/dist/es/views/Statistic/StatisticGroup.js": 850,
      "node_modules/semantic-ui-react/dist/es/views/Statistic/StatisticLabel.js": 851,
      "node_modules/semantic-ui-react/dist/es/views/Statistic/StatisticValue.js": 852,
      "node_modules/semantic-ui-react/dist/es/views/Statistic/index.js": 853,
      "node_modules/semantic-ui-react/node_modules/@babel/runtime/helpers/objectWithoutProperties.js": 854,
      "node_modules/semantic-ui-react/node_modules/@babel/runtime/helpers/objectWithoutPropertiesLoose.js": 855
    },
    "usedIds": {
      "0": 0,
      "1": 1,
      "2": 2,
      "3": 3,
      "4": 4,
      "5": 5,
      "6": 6,
      "7": 7,
      "8": 8,
      "9": 9,
      "10": 10,
      "11": 11,
      "12": 12,
      "13": 13,
      "14": 14,
      "15": 15,
      "16": 16,
      "17": 17,
      "18": 18,
      "19": 19,
      "20": 20,
      "21": 21,
      "22": 22,
      "23": 23,
      "24": 24,
      "25": 25,
      "26": 26,
      "27": 27,
      "28": 28,
      "29": 29,
      "30": 30,
      "31": 31,
      "32": 32,
      "33": 33,
      "34": 34,
      "35": 35,
      "36": 36,
      "37": 37,
      "38": 38,
      "39": 39,
      "40": 40,
      "41": 41,
      "42": 42,
      "43": 43,
      "44": 44,
      "45": 45,
      "46": 46,
      "47": 47,
      "48": 48,
      "49": 49,
      "50": 50,
      "51": 51,
      "52": 52,
      "53": 53,
      "54": 54,
      "55": 55,
      "56": 56,
      "57": 57,
      "58": 58,
      "59": 59,
      "60": 60,
      "61": 61,
      "62": 62,
      "63": 63,
      "64": 64,
      "65": 65,
      "66": 66,
      "67": 67,
      "68": 68,
      "69": 69,
      "70": 70,
      "71": 71,
      "72": 72,
      "73": 73,
      "74": 74,
      "75": 75,
      "76": 76,
      "77": 77,
      "78": 78,
      "79": 79,
      "80": 80,
      "81": 81,
      "82": 82,
      "83": 83,
      "84": 84,
      "85": 85,
      "86": 86,
      "87": 87,
      "88": 88,
      "89": 89,
      "90": 90,
      "91": 91,
      "92": 92,
      "93": 93,
      "94": 94,
      "95": 95,
      "96": 96,
      "97": 97,
      "98": 98,
      "99": 99,
      "100": 100,
      "101": 101,
      "102": 102,
      "103": 103,
      "104": 104,
      "105": 105,
      "106": 106,
      "107": 107,
      "108": 108,
      "109": 109,
      "110": 110,
      "111": 111,
      "112": 112,
      "113": 113,
      "114": 114,
      "115": 115,
      "116": 116,
      "117": 117,
      "118": 118,
      "119": 119,
      "120": 120,
      "121": 121,
      "122": 122,
      "123": 123,
      "124": 124,
      "125": 125,
      "126": 126,
      "127": 127,
      "128": 128,
      "129": 129,
      "130": 130,
      "131": 131,
      "132": 132,
      "133": 133,
      "134": 134,
      "135": 135,
      "136": 136,
      "137": 137,
      "138": 138,
      "139": 139,
      "140": 140,
      "141": 141,
      "142": 142,
      "143": 143,
      "144": 144,
      "145": 145,
      "146": 146,
      "147": 147,
      "148": 148,
      "149": 149,
      "150": 150,
      "151": 151,
      "152": 152,
      "153": 153,
      "154": 154,
      "155": 155,
      "156": 156,
      "157": 157,
      "158": 158,
      "159": 159,
      "160": 160,
      "161": 161,
      "162": 162,
      "163": 163,
      "164": 164,
      "165": 165,
      "166": 166,
      "167": 167,
      "168": 168,
      "169": 169,
      "170": 170,
      "171": 171,
      "172": 172,
      "173": 173,
      "174": 174,
      "175": 175,
      "176": 176,
      "177": 177,
      "178": 178,
      "179": 179,
      "180": 180,
      "181": 181,
      "182": 182,
      "183": 183,
      "184": 184,
      "185": 185,
      "186": 186,
      "187": 187,
      "188": 188,
      "189": 189,
      "190": 190,
      "191": 191,
      "192": 192,
      "193": 193,
      "194": 194,
      "195": 195,
      "196": 196,
      "197": 197,
      "198": 198,
      "199": 199,
      "200": 200,
      "201": 201,
      "202": 202,
      "203": 203,
      "204": 204,
      "205": 205,
      "206": 206,
      "207": 207,
      "208": 208,
      "209": 209,
      "210": 210,
      "211": 211,
      "212": 212,
      "213": 213,
      "214": 214,
      "215": 215,
      "216": 216,
      "217": 217,
      "218": 218,
      "219": 219,
      "220": 220,
      "221": 221,
      "222": 222,
      "223": 223,
      "224": 224,
      "225": 225,
      "226": 226,
      "227": 227,
      "228": 228,
      "229": 229,
      "230": 230,
      "231": 231,
      "232": 232,
      "233": 233,
      "234": 234,
      "235": 235,
      "236": 236,
      "237": 237,
      "238": 238,
      "239": 239,
      "240": 240,
      "241": 241,
      "242": 242,
      "243": 243,
      "244": 244,
      "245": 245,
      "246": 246,
      "247": 247,
      "248": 248,
      "249": 249,
      "250": 250,
      "251": 251,
      "252": 252,
      "253": 253,
      "254": 254,
      "255": 255,
      "256": 256,
      "257": 257,
      "258": 258,
      "259": 259,
      "260": 260,
      "261": 261,
      "262": 262,
      "263": 263,
      "264": 264,
      "265": 265,
      "266": 266,
      "267": 267,
      "268": 268,
      "269": 269,
      "270": 270,
      "271": 271,
      "272": 272,
      "273": 273,
      "274": 274,
      "275": 275,
      "276": 276,
      "277": 277,
      "278": 278,
      "279": 279,
      "280": 280,
      "281": 281,
      "282": 282,
      "283": 283,
      "284": 284,
      "285": 285,
      "286": 286,
      "287": 287,
      "288": 288,
      "289": 289,
      "290": 290,
      "291": 291,
      "292": 292,
      "293": 293,
      "294": 294,
      "295": 295,
      "296": 296,
      "297": 297,
      "298": 298,
      "299": 299,
      "300": 300,
      "301": 301,
      "302": 302,
      "303": 303,
      "304": 304,
      "305": 305,
      "306": 306,
      "307": 307,
      "308": 308,
      "309": 309,
      "310": 310,
      "311": 311,
      "312": 312,
      "313": 313,
      "314": 314,
      "315": 315,
      "316": 316,
      "317": 317,
      "318": 318,
      "319": 319,
      "320": 320,
      "321": 321,
      "322": 322,
      "323": 323,
      "324": 324,
      "325": 325,
      "326": 326,
      "327": 327,
      "328": 328,
      "329": 329,
      "330": 330,
      "331": 331,
      "332": 332,
      "333": 333,
      "334": 334,
      "335": 335,
      "336": 336,
      "337": 337,
      "338": 338,
      "339": 339,
      "340": 340,
      "341": 341,
      "342": 342,
      "343": 343,
      "344": 344,
      "345": 345,
      "346": 346,
      "347": 347,
      "348": 348,
      "349": 349,
      "350": 350,
      "351": 351,
      "352": 352,
      "353": 353,
      "354": 354,
      "355": 355,
      "356": 356,
      "357": 357,
      "358": 358,
      "359": 359,
      "360": 360,
      "361": 361,
      "362": 362,
      "363": 363,
      "364": 364,
      "365": 365,
      "366": 366,
      "367": 367,
      "368": 368,
      "369": 369,
      "370": 370,
      "371": 371,
      "372": 372,
      "373": 373,
      "374": 374,
      "375": 375,
      "376": 376,
      "377": 377,
      "378": 378,
      "379": 379,
      "380": 380,
      "381": 381,
      "382": 382,
      "383": 383,
      "384": 384,
      "385": 385,
      "386": 386,
      "387": 387,
      "388": 388,
      "389": 389,
      "390": 390,
      "391": 391,
      "392": 392,
      "393": 393,
      "394": 394,
      "395": 395,
      "396": 396,
      "397": 397,
      "398": 398,
      "399": 399,
      "400": 400,
      "401": 401,
      "402": 402,
      "403": 403,
      "404": 404,
      "405": 405,
      "406": 406,
      "407": 407,
      "408": 408,
      "409": 409,
      "410": 410,
      "411": 411,
      "412": 412,
      "413": 413,
      "414": 414,
      "415": 415,
      "416": 416,
      "417": 417,
      "418": 418,
      "419": 419,
      "420": 420,
      "421": 421,
      "422": 422,
      "423": 423,
      "424": 424,
      "425": 425,
      "426": 426,
      "427": 427,
      "428": 428,
      "429": 429,
      "430": 430,
      "431": 431,
      "432": 432,
      "433": 433,
      "434": 434,
      "435": 435,
      "436": 436,
      "437": 437,
      "438": 438,
      "439": 439,
      "440": 440,
      "441": 441,
      "442": 442,
      "443": 443,
      "444": 444,
      "445": 445,
      "446": 446,
      "447": 447,
      "448": 448,
      "449": 449,
      "450": 450,
      "451": 451,
      "452": 452,
      "453": 453,
      "454": 454,
      "455": 455,
      "456": 456,
      "457": 457,
      "458": 458,
      "459": 459,
      "460": 460,
      "461": 461,
      "462": 462,
      "463": 463,
      "464": 464,
      "465": 465,
      "466": 466,
      "467": 467,
      "468": 468,
      "469": 469,
      "470": 470,
      "471": 471,
      "472": 472,
      "473": 473,
      "474": 474,
      "475": 475,
      "476": 476,
      "477": 477,
      "478": 478,
      "479": 479,
      "480": 480,
      "481": 481,
      "482": 482,
      "483": 483,
      "484": 484,
      "485": 485,
      "486": 486,
      "487": 487,
      "488": 488,
      "489": 489,
      "490": 490,
      "491": 491,
      "492": 492,
      "493": 493,
      "494": 494,
      "495": 495,
      "496": 496,
      "497": 497,
      "498": 498,
      "499": 499,
      "500": 500,
      "501": 501,
      "502": 502,
      "503": 503,
      "504": 504,
      "505": 505,
      "506": 506,
      "507": 507,
      "508": 508,
      "509": 509,
      "510": 510,
      "511": 511,
      "512": 512,
      "513": 513,
      "514": 514,
      "515": 515,
      "516": 516,
      "517": 517,
      "518": 518,
      "519": 519,
      "520": 520,
      "521": 521,
      "522": 522,
      "523": 523,
      "524": 524,
      "525": 525,
      "526": 526,
      "527": 527,
      "528": 528,
      "529": 529,
      "530": 530,
      "531": 531,
      "532": 532,
      "533": 533,
      "534": 534,
      "535": 535,
      "536": 536,
      "537": 537,
      "538": 538,
      "539": 539,
      "540": 540,
      "541": 541,
      "542": 542,
      "543": 543,
      "544": 544,
      "545": 545,
      "546": 546,
      "547": 547,
      "548": 548,
      "549": 549,
      "550": 550,
      "551": 551,
      "552": 552,
      "553": 553,
      "554": 554,
      "555": 555,
      "556": 556,
      "557": 557,
      "558": 558,
      "559": 559,
      "560": 560,
      "561": 561,
      "562": 562,
      "563": 563,
      "564": 564,
      "565": 565,
      "566": 566,
      "567": 567,
      "568": 568,
      "569": 569,
      "570": 570,
      "571": 571,
      "572": 572,
      "573": 573,
      "574": 574,
      "575": 575,
      "576": 576,
      "577": 577,
      "578": 578,
      "579": 579,
      "580": 580,
      "581": 581,
      "582": 582,
      "583": 583,
      "584": 584,
      "585": 585,
      "586": 586,
      "587": 587,
      "588": 588,
      "589": 589,
      "590": 590,
      "591": 591,
      "592": 592,
      "593": 593,
      "594": 594,
      "595": 595,
      "596": 596,
      "597": 597,
      "598": 598,
      "599": 599,
      "600": 600,
      "601": 601,
      "602": 602,
      "603": 603,
      "604": 604,
      "605": 605,
      "606": 606,
      "607": 607,
      "608": 608,
      "609": 609,
      "610": 610,
      "611": 611,
      "612": 612,
      "613": 613,
      "614": 614,
      "615": 615,
      "616": 616,
      "617": 617,
      "618": 618,
      "619": 619,
      "620": 620,
      "621": 621,
      "622": 622,
      "623": 623,
      "624": 624,
      "625": 625,
      "626": 626,
      "627": 627,
      "628": 628,
      "629": 629,
      "630": 630,
      "631": 631,
      "632": 632,
      "633": 633,
      "634": 634,
      "635": 635,
      "636": 636,
      "637": 637,
      "638": 638,
      "639": 639,
      "640": 640,
      "641": 641,
      "642": 642,
      "643": 643,
      "644": 644,
      "645": 645,
      "646": 646,
      "647": 647,
      "648": 648,
      "649": 649,
      "650": 650,
      "651": 651,
      "652": 652,
      "653": 653,
      "654": 654,
      "655": 655,
      "656": 656,
      "657": 657,
      "658": 658,
      "659": 659,
      "660": 660,
      "661": 661,
      "662": 662,
      "663": 663,
      "664": 664,
      "665": 665,
      "666": 666,
      "667": 667,
      "668": 668,
      "669": 669,
      "670": 670,
      "671": 671,
      "672": 672,
      "673": 673,
      "674": 674,
      "675": 675,
      "676": 676,
      "677": 677,
      "678": 678,
      "679": 679,
      "680": 680,
      "681": 681,
      "682": 682,
      "683": 683,
      "684": 684,
      "685": 685,
      "686": 686,
      "687": 687,
      "688": 688,
      "689": 689,
      "690": 690,
      "691": 691,
      "692": 692,
      "693": 693,
      "694": 694,
      "695": 695,
      "696": 696,
      "697": 697,
      "698": 698,
      "699": 699,
      "700": 700,
      "701": 701,
      "702": 702,
      "703": 703,
      "704": 704,
      "705": 705,
      "706": 706,
      "707": 707,
      "708": 708,
      "709": 709,
      "710": 710,
      "711": 711,
      "712": 712,
      "713": 713,
      "714": 714,
      "715": 715,
      "716": 716,
      "717": 717,
      "718": 718,
      "719": 719,
      "720": 720,
      "721": 721,
      "722": 722,
      "723": 723,
      "724": 724,
      "725": 725,
      "726": 726,
      "727": 727,
      "728": 728,
      "729": 729,
      "730": 730,
      "731": 731,
      "732": 732,
      "733": 733,
      "734": 734,
      "735": 735,
      "736": 736,
      "737": 737,
      "738": 738,
      "739": 739,
      "740": 740,
      "741": 741,
      "742": 742,
      "743": 743,
      "744": 744,
      "745": 745,
      "746": 746,
      "747": 747,
      "748": 748,
      "749": 749,
      "750": 750,
      "751": 751,
      "752": 752,
      "753": 753,
      "754": 754,
      "755": 755,
      "756": 756,
      "757": 757,
      "758": 758,
      "759": 759,
      "760": 760,
      "761": 761,
      "762": 762,
      "763": 763,
      "764": 764,
      "765": 765,
      "766": 766,
      "767": 767,
      "768": 768,
      "769": 769,
      "770": 770,
      "771": 771,
      "772": 772,
      "773": 773,
      "774": 774,
      "775": 775,
      "776": 776,
      "777": 777,
      "778": 778,
      "779": 779,
      "780": 780,
      "781": 781,
      "782": 782,
      "783": 783,
      "784": 784,
      "785": 785,
      "786": 786,
      "787": 787,
      "788": 788,
      "789": 789,
      "790": 790,
      "791": 791,
      "792": 792,
      "793": 793,
      "794": 794,
      "795": 795,
      "796": 796,
      "797": 797,
      "798": 798,
      "799": 799,
      "800": 800,
      "801": 801,
      "802": 802,
      "803": 803,
      "804": 804,
      "805": 805,
      "806": 806,
      "807": 807,
      "808": 808,
      "809": 809,
      "810": 810,
      "811": 811,
      "812": 812,
      "813": 813,
      "814": 814,
      "815": 815,
      "816": 816,
      "817": 817,
      "818": 818,
      "819": 819,
      "820": 820,
      "821": 821,
      "822": 822,
      "823": 823,
      "824": 824,
      "825": 825,
      "826": 826,
      "827": 827,
      "828": 828,
      "829": 829,
      "830": 830,
      "831": 831,
      "832": 832,
      "833": 833,
      "834": 834,
      "835": 835,
      "836": 836,
      "837": 837,
      "838": 838,
      "839": 839,
      "840": 840,
      "841": 841,
      "842": 842,
      "843": 843,
      "844": 844,
      "845": 845,
      "846": 846,
      "847": 847,
      "848": 848,
      "849": 849,
      "850": 850,
      "851": 851,
      "852": 852,
      "853": 853,
      "854": 854,
      "855": 855
    }
  },
  "chunks": {
    "byName": {
      "commons": 0,
      "static/runtime/webpack.js": 1,
      "styles": 2,
      "static/runtime/main.js": 3,
      "static/qHEL24ROQ48cJaY9Zb42i/pages/_app.js": 4,
      "static/qHEL24ROQ48cJaY9Zb42i/pages/_index.js": 5,
      "static/qHEL24ROQ48cJaY9Zb42i/pages/add-company.js": 6,
      "static/qHEL24ROQ48cJaY9Zb42i/pages/company-contact/category.js": 7,
      "static/qHEL24ROQ48cJaY9Zb42i/pages/company-contact/company.js": 8,
      "static/qHEL24ROQ48cJaY9Zb42i/pages/company-contact.js": 9,
      "static/qHEL24ROQ48cJaY9Zb42i/pages/index.js": 10,
      "static/qHEL24ROQ48cJaY9Zb42i/pages/_error.js": 11
    },
    "bySource": {},
    "usedIds": [
      0,
      1,
      10,
      11,
      2,
      3,
      4,
      5,
      6,
      7,
      8,
      9
    ]
  }
}